setup.cfg
setup.py
scripts/jupyter-contrib-nbextension
src/helloWorld_nb_extension.egg-info/PKG-INFO
src/helloWorld_nb_extension.egg-info/SOURCES.txt
src/helloWorld_nb_extension.egg-info/dependency_links.txt
src/helloWorld_nb_extension.egg-info/entry_points.txt
src/helloWorld_nb_extension.egg-info/not-zip-safe
src/helloWorld_nb_extension.egg-info/requires.txt
src/helloWorld_nb_extension.egg-info/top_level.txt
src/jupyter_contrib_nbextensions/__init__.py
src/jupyter_contrib_nbextensions/application.py
src/jupyter_contrib_nbextensions/install.py
src/jupyter_contrib_nbextensions/migrate.py
src/jupyter_contrib_nbextensions/config_scripts/__init__.py
src/jupyter_contrib_nbextensions/config_scripts/highlight_html_cfg.py
src/jupyter_contrib_nbextensions/config_scripts/highlight_latex_cfg.py
src/jupyter_contrib_nbextensions/nbconvert_support/__init__.py
src/jupyter_contrib_nbextensions/nbconvert_support/embedhtml.py
src/jupyter_contrib_nbextensions/nbconvert_support/pp_highlighter.py
src/jupyter_contrib_nbextensions/nbconvert_support/pre_codefolding.py
src/jupyter_contrib_nbextensions/nbconvert_support/pre_collapsible_headings.py
src/jupyter_contrib_nbextensions/nbconvert_support/pre_pymarkdown.py
src/jupyter_contrib_nbextensions/nbconvert_support/pre_svg2pdf.py
src/jupyter_contrib_nbextensions/nbconvert_support/strip_output_prompt.py
src/jupyter_contrib_nbextensions/nbconvert_support/toc2.py