Metadata-Version: 1.1
Name: helloWorld-nb-extension
Version: 0.2
Summary: Simple hello world extension for jupyter notebook.
Home-page: UNKNOWN
Author: Belal Amin
Author-email: belalmostafa30@gmail.com
License: UNKNOWN
Keywords: IPython,Jupyter,notebook
Platform: Any
Classifier: Development Status :: 1 - Planning
Classifier: Intended Audience :: End Users/Desktop
Classifier: Intended Audience :: Science/Research
Classifier: License :: OSI Approved :: BSD License
Classifier: Natural Language :: English
Classifier: Operating System :: OS Independent
Classifier: Programming Language :: JavaScript
Classifier: Programming Language :: Python
Classifier: Topic :: Utilities
